pletyvo/__init__.py
pletyvo/abc.py
pletyvo/dapp_service.py
pletyvo/delivery_service.py
pletyvo/engine.py
pletyvo/py.typed
pletyvo/service.py
pletyvo/dapp/__init__.py
pletyvo/dapp/abc.py
pletyvo/dapp/ed25519.py
pletyvo/dapp/event.py
pletyvo/dapp/hash.py
pletyvo/delivery/__init__.py
pletyvo/delivery/abc.py
pletyvo/delivery/channel.py
pletyvo/delivery/event_type.py
pletyvo/delivery/message.py
pletyvo/delivery/post.py
pletyvo/internal/__init__.py
pletyvo/internal/base64.py
pletyvo/internal/sanitizer.py
pletyvo/internal/serializer.py
pletyvo/internal/uuid.py
pletyvo/internal/validators.py
pletyvo/types/__init__.py
pletyvo/types/_types.py
pletyvo/types/query_option.py
pletyvo-0.1.0.dist-info/licenses/LICENSE
pletyvo-0.1.0.dist-info/METADATA
pletyvo-0.1.0.dist-info/WHEEL
pletyvo-0.1.0.dist-info/top_level.txt
pletyvo-0.1.0.dist-info/RECORD
