Metadata-Version: 2.4
Name: pletyvo
Version: 0.1.0
Summary: Typed, async‑first Python client for the Pletyvo decentralized platform and it's protocols (Python ≥ 3.9)
License: MIT License
Project-URL: Homepage, https://pletyvo.osyah.com
Project-URL: Documentation, https://pletyvo.osyah.com
Project-URL: Repository, https://github.com/osyah/py-pletyvo.git
Project-URL: Issues, https://github.com/osyah/py-pletyvo/issues
Classifier: Development Status :: 3 - Alpha
Classifier: Intended Audience :: Developers
Classifier: Topic :: Software Development :: Build Tools
Classifier: License :: OSI Approved :: MIT License
Classifier: Programming Language :: Python :: Implementation :: CPython
Classifier: Programming Language :: Python :: 3.9
Classifier: Programming Language :: Python :: 3.10
Classifier: Programming Language :: Python :: 3.11
Classifier: Programming Language :: Python :: 3.12
Classifier: Programming Language :: Python :: 3.13
Classifier: Typing :: Typed
Requires-Python: >=3.9
License-File: LICENSE
Requires-Dist: setuptools~=71.0.4
Requires-Dist: aiohttp~=3.10.6
Requires-Dist: attrs~=24.2.0
Requires-Dist: cryptography~=43.0.3
Requires-Dist: blake3~=0.4.1
Requires-Dist: classes>=0.4.1
Requires-Dist: uuid-utils>=0.11.0
Dynamic: license-file
